alexa_teacher_models/__init__.py
alexa_teacher_models/configuration_atm.py
alexa_teacher_models/modeling_atm.py
alexa_teacher_models/tokenization_atm.py
alexa_teacher_models/scripts/__init__.py
alexa_teacher_models/scripts/finetune.py
alexa_teacher_models/scripts/generate_outputs.py
alexa_teacher_models/scripts/metrics.py
alexa_teacher_models/scripts/preproc.py
alexa_teacher_models/scripts/repl.py
alexa_teacher_models/scripts/train_utils.py
alexa_teacher_models/scripts/deepspeed/zero2.json
alexa_teacher_models/scripts/deepspeed/zero3-offload.json
alexa_teacher_models/scripts/deepspeed/zero3.json
alexa_teacher_models-1.0.1.dist-info/LICENSE
alexa_teacher_models-1.0.1.dist-info/METADATA
alexa_teacher_models-1.0.1.dist-info/NOTICE
alexa_teacher_models-1.0.1.dist-info/WHEEL
alexa_teacher_models-1.0.1.dist-info/top_level.txt
alexa_teacher_models-1.0.1.dist-info/RECORD
