Metadata-Version: 2.1
Name: alexa-teacher-models
Version: 1.0.1
Summary: Alexa Teacher Models
Home-page: https://github.com/alexa/alexa-teacher-models
Author: amazon-alexa
Author-email: ssoltan@amazon.com
License: Apache 2.0
Keywords: deep-learning,nlp,pytorch,llm
Classifier: Development Status :: 3 - Alpha
Classifier: Environment :: Console
Classifier: Intended Audience :: Developers
Classifier: Intended Audience :: Science/Research
Classifier: License :: OSI Approved :: Apache Software License
Classifier: Natural Language :: English
Classifier: Operating System :: OS Independent
Classifier: Programming Language :: Python :: 3.7
Classifier: Programming Language :: Python :: 3.8
Classifier: Programming Language :: Python :: 3.9
Classifier: Programming Language :: Python :: 3.10
Classifier: Topic :: Scientific/Engineering :: Artificial Intelligence
License-File: LICENSE
License-File: NOTICE
Requires-Dist: numpy
Requires-Dist: transformers
Requires-Dist: sentencepiece (>=0.1.95)
Requires-Dist: torch (<2.0,>=1.7)
Requires-Dist: protobuf (<3.21.0)
Provides-Extra: ft
Requires-Dist: datasets ; extra == 'ft'
Requires-Dist: evaluate ; extra == 'ft'
Requires-Dist: deepspeed ; extra == 'ft'
Requires-Dist: accelerate ; extra == 'ft'
Requires-Dist: sacrebleu ; extra == 'ft'
Requires-Dist: tensorboard ; extra == 'ft'
Provides-Extra: repl
Requires-Dist: prompt-toolkit ; extra == 'repl'
Provides-Extra: sum
Requires-Dist: nltk ; extra == 'sum'
Requires-Dist: rouge-score (>=0.1.2) ; extra == 'sum'
Provides-Extra: test
Requires-Dist: pytest ; extra == 'test'
